stc_converter/__init__.py
stc_converter/listenner.py
stc_converter/stc.py
stc_converter-0.1.dist-info/LICENSE
stc_converter-0.1.dist-info/METADATA
stc_converter-0.1.dist-info/WHEEL
stc_converter-0.1.dist-info/top_level.txt
stc_converter-0.1.dist-info/RECORD
