Metadata-Version: 2.1
Name: stc-converter
Version: 0.1
Summary: A simple speech to command converter
Home-page: https://github.com/SamuelSGSouza/STC-converter.git
Author: Samuel G Souza
Author-email: samuels.g.desouza@gmail.com
License: MIT
License-File: LICENSE
Requires-Dist: certifi
Requires-Dist: charset-normalizer
Requires-Dist: click
Requires-Dist: colorama
Requires-Dist: idna
Requires-Dist: joblib
Requires-Dist: nltk
Requires-Dist: PyAudio
Requires-Dist: regex
Requires-Dist: requests
Requires-Dist: SpeechRecognition
Requires-Dist: tqdm
Requires-Dist: typing-extensions
Requires-Dist: urllib3
